dagster_gcp_pandas/__init__.py
dagster_gcp_pandas/py.typed
dagster_gcp_pandas/version.py
dagster_gcp_pandas/bigquery/__init__.py
dagster_gcp_pandas/bigquery/bigquery_pandas_type_handler.py
dagster_gcp_pandas-0.28.13.dist-info/licenses/LICENSE
dagster_gcp_pandas-0.28.13.dist-info/METADATA
dagster_gcp_pandas-0.28.13.dist-info/WHEEL
dagster_gcp_pandas-0.28.13.dist-info/top_level.txt
dagster_gcp_pandas-0.28.13.dist-info/RECORD
